netunicorn/director/infrastructure/__init__.py
netunicorn/director/infrastructure/__main__.py
netunicorn/director/infrastructure/kernel.py
netunicorn/director/infrastructure/server.py
netunicorn/director/infrastructure/tasks.py
netunicorn/director/infrastructure/connectors/__init__.py
netunicorn/director/infrastructure/connectors/dummy.py
netunicorn/director/infrastructure/connectors/rest/__init__.py
netunicorn/director/infrastructure/connectors/rest/simple_rest.py
netunicorn_director_infrastructure-0.4.0.dist-info/LICENSE
netunicorn_director_infrastructure-0.4.0.dist-info/METADATA
netunicorn_director_infrastructure-0.4.0.dist-info/WHEEL
netunicorn_director_infrastructure-0.4.0.dist-info/top_level.txt
netunicorn_director_infrastructure-0.4.0.dist-info/RECORD
