Metadata-Version: 2.1
Name: netunicorn-director-infrastructure
Version: 0.4.0
Summary: netunicorn infrastructure module
Author-email: Roman Beltiukov <rbeltiukov@ucsb.edu>
License: MIT
Keywords: netunicorn
Classifier: Programming Language :: Python :: 3
Requires-Python: >=3.10
License-File: LICENSE
Requires-Dist: fastapi
Requires-Dist: netunicorn-base <0.5.0,>=0.4.0
Requires-Dist: uvicorn
Requires-Dist: asyncpg
Requires-Dist: pyyaml
Requires-Dist: returns
Requires-Dist: aiohttp
